ciscomobilityexpress/__init__.py
ciscomobilityexpress/ciscome.py
ciscomobilityexpress/constants.py
ciscomobilityexpress/exceptions.py
ciscomobilityexpress-1.0.2.dist-info/LICENSE
ciscomobilityexpress-1.0.2.dist-info/METADATA
ciscomobilityexpress-1.0.2.dist-info/WHEEL
ciscomobilityexpress-1.0.2.dist-info/top_level.txt
ciscomobilityexpress-1.0.2.dist-info/RECORD
