Metadata-Version: 2.1
Name: ciscomobilityexpress
Version: 1.0.2
Summary: Module to interact with Cisco Mobility Express APIs to fetch connected devices.
Home-page: https://github.com/fbradyirl/ciscomobilityexpress
Author: Finbarr Brady
Author-email: fbradyirl@github.io
License: MIT license
Keywords: ciscomobilityexpress
Platform: UNKNOWN
Classifier: Development Status :: 2 - Pre-Alpha
Classifier: Intended Audience :: Developers
Classifier: License :: OSI Approved :: MIT License
Classifier: Natural Language :: English
Classifier: Programming Language :: Python :: 3.6
Classifier: Programming Language :: Python :: 3.7
Requires-Dist: requests (>=2.21.0)
